[
	{
		"name": "Square",
		"width": 500,
		"height": 500,
		"number": 1,
		"id": "664nsvln6",
		"state": {
			"version": "5.3.0",
			"objects": [
				{
					"type": "rect",
					"version": "5.3.0",
					"originX": "left",
					"originY": "top",
					"left": 283.5,
					"top": 186.5,
					"width": 500,
					"height": 500,
					"fill": "#fff",
					"stroke": null,
					"strokeWidth": 1,
					"strokeDashArray": null,
					"strokeLineCap": "butt",
					"strokeDashOffset": 0,
					"strokeLineJoin": "miter",
					"strokeUniform": false,
					"strokeMiterLimit": 4,
					"scaleX": 1,
					"scaleY": 1,
					"angle": 0,
					"flipX": false,
					"flipY": false,
					"opacity": 1,
					"shadow": null,
					"visible": true,
					"backgroundColor": "",
					"fillRule": "nonzero",
					"paintFirst": "fill",
					"globalCompositeOperation": "source-over",
					"skewX": 0,
					"skewY": 0,
					"rx": 0,
					"ry": 0,
					"data": { "type": "artboard", "id": "664nsvln6" },
					"selectable": false
				},
				{
					"type": "textbox",
					"version": "5.3.0",
					"originX": "left",
					"originY": "top",
					"left": 365.72,
					"top": 221.33,
					"width": 110.28,
					"height": 22.6,
					"fill": "rgb(0,0,0)",
					"stroke": null,
					"strokeWidth": 1,
					"strokeDashArray": null,
					"strokeLineCap": "butt",
					"strokeDashOffset": 0,
					"strokeLineJoin": "miter",
					"strokeUniform": false,
					"strokeMiterLimit": 4,
					"scaleX": 3.2,
					"scaleY": 3.2,
					"angle": 0,
					"flipX": false,
					"flipY": false,
					"opacity": 1,
					"shadow": null,
					"visible": true,
					"backgroundColor": "",
					"fillRule": "nonzero",
					"paintFirst": "fill",
					"globalCompositeOperation": "source-over",
					"skewX": 0,
					"skewY": 0,
					"fontFamily": "Inter",
					"fontWeight": "normal",
					"fontSize": 20,
					"text": "Artboard 1",
					"underline": false,
					"overline": false,
					"linethrough": false,
					"textAlign": "left",
					"fontStyle": "normal",
					"lineHeight": 1.16,
					"textBackgroundColor": "",
					"charSpacing": 0,
					"styles": [],
					"direction": "ltr",
					"path": null,
					"pathStartOffset": 0,
					"pathSide": "left",
					"pathAlign": "baseline",
					"minWidth": 20,
					"splitByGrapheme": false,
					"selectable": true
				},
				{
					"type": "image",
					"version": "5.3.0",
					"originX": "left",
					"originY": "top",
					"left": 295.13,
					"top": 331.27,
					"width": 4762,
					"height": 3566,
					"fill": "rgb(0,0,0)",
					"stroke": null,
					"strokeWidth": 0,
					"strokeDashArray": null,
					"strokeLineCap": "butt",
					"strokeDashOffset": 0,
					"strokeLineJoin": "miter",
					"strokeUniform": false,
					"strokeMiterLimit": 4,
					"scaleX": 0.1,
					"scaleY": 0.09,
					"angle": 0,
					"flipX": false,
					"flipY": false,
					"opacity": 1,
					"shadow": null,
					"visible": true,
					"backgroundColor": "",
					"fillRule": "nonzero",
					"paintFirst": "fill",
					"globalCompositeOperation": "source-over",
					"skewX": 0,
					"skewY": 0,
					"cropX": 0,
					"cropY": 0,
					"selectable": true,
					"src": "https://ik.imagekit.io/mfsshclpl/A%20man%20and%20a%20woman%20walking%20in%20the%20desert.jpg?updatedAt=1699352535525",
					"crossOrigin": "anonymous",
					"filters": []
				}
			]
		}
	},
	{
		"name": "Rectangle",
		"width": 500,
		"height": 250,
		"number": 1,
		"id": "vd3gpna84",
		"state": {
			"version": "5.3.0",
			"objects": [
				{
					"type": "rect",
					"version": "5.3.0",
					"originX": "left",
					"originY": "top",
					"left": 283.5,
					"top": 311.5,
					"width": 500,
					"height": 250,
					"fill": "#fff",
					"stroke": null,
					"strokeWidth": 1,
					"strokeDashArray": null,
					"strokeLineCap": "butt",
					"strokeDashOffset": 0,
					"strokeLineJoin": "miter",
					"strokeUniform": false,
					"strokeMiterLimit": 4,
					"scaleX": 1,
					"scaleY": 1,
					"angle": 0,
					"flipX": false,
					"flipY": false,
					"opacity": 1,
					"shadow": null,
					"visible": true,
					"backgroundColor": "",
					"fillRule": "nonzero",
					"paintFirst": "fill",
					"globalCompositeOperation": "source-over",
					"skewX": 0,
					"skewY": 0,
					"rx": 0,
					"ry": 0,
					"data": { "type": "artboard", "id": "vd3gpna84" },
					"selectable": false
				},
				{
					"type": "textbox",
					"version": "5.3.0",
					"originX": "left",
					"originY": "top",
					"left": 398.81,
					"top": 314.22,
					"width": 116.26,
					"height": 22.6,
					"fill": "rgb(0,0,0)",
					"stroke": null,
					"strokeWidth": 1,
					"strokeDashArray": null,
					"strokeLineCap": "butt",
					"strokeDashOffset": 0,
					"strokeLineJoin": "miter",
					"strokeUniform": false,
					"strokeMiterLimit": 4,
					"scaleX": 2.48,
					"scaleY": 2.48,
					"angle": 0,
					"flipX": false,
					"flipY": false,
					"opacity": 1,
					"shadow": null,
					"visible": true,
					"backgroundColor": "",
					"fillRule": "nonzero",
					"paintFirst": "fill",
					"globalCompositeOperation": "source-over",
					"skewX": 0,
					"skewY": 0,
					"fontFamily": "Inter",
					"fontWeight": "normal",
					"fontSize": 20,
					"text": "Artboard 2",
					"underline": false,
					"overline": false,
					"linethrough": false,
					"textAlign": "left",
					"fontStyle": "normal",
					"lineHeight": 1.16,
					"textBackgroundColor": "",
					"charSpacing": 0,
					"styles": [],
					"direction": "ltr",
					"path": null,
					"pathStartOffset": 0,
					"pathSide": "left",
					"pathAlign": "baseline",
					"minWidth": 20,
					"splitByGrapheme": false,
					"selectable": true
				},
				{
					"type": "image",
					"version": "5.3.0",
					"originX": "left",
					"originY": "top",
					"left": 402.71,
					"top": 367.41,
					"width": 4762,
					"height": 3566,
					"fill": "rgb(0,0,0)",
					"stroke": null,
					"strokeWidth": 0,
					"strokeDashArray": null,
					"strokeLineCap": "butt",
					"strokeDashOffset": 0,
					"strokeLineJoin": "miter",
					"strokeUniform": false,
					"strokeMiterLimit": 4,
					"scaleX": 0.05,
					"scaleY": 0.05,
					"angle": 0,
					"flipX": false,
					"flipY": false,
					"opacity": 1,
					"shadow": null,
					"visible": true,
					"backgroundColor": "",
					"fillRule": "nonzero",
					"paintFirst": "fill",
					"globalCompositeOperation": "source-over",
					"skewX": 0,
					"skewY": 0,
					"cropX": 0,
					"cropY": 0,
					"selectable": true,
					"src": "https://ik.imagekit.io/mfsshclpl/A%20man%20and%20a%20woman%20walking%20in%20the%20desert.jpg?updatedAt=1699352535525",
					"crossOrigin": "anonymous",
					"filters": []
				}
			]
		}
	},
	{
		"name": "Rectangle 2",
		"width": 250,
		"height": 500,
		"number": 1,
		"id": "b5dfw2ite",
		"state": {
			"version": "5.3.0",
			"objects": [
				{
					"type": "rect",
					"version": "5.3.0",
					"originX": "left",
					"originY": "top",
					"left": 408.5,
					"top": 186.5,
					"width": 250,
					"height": 500,
					"fill": "#fff",
					"stroke": null,
					"strokeWidth": 1,
					"strokeDashArray": null,
					"strokeLineCap": "butt",
					"strokeDashOffset": 0,
					"strokeLineJoin": "miter",
					"strokeUniform": false,
					"strokeMiterLimit": 4,
					"scaleX": 1,
					"scaleY": 1,
					"angle": 0,
					"flipX": false,
					"flipY": false,
					"opacity": 1,
					"shadow": null,
					"visible": true,
					"backgroundColor": "",
					"fillRule": "nonzero",
					"paintFirst": "fill",
					"globalCompositeOperation": "source-over",
					"skewX": 0,
					"skewY": 0,
					"rx": 0,
					"ry": 0,
					"data": { "type": "artboard", "id": "b5dfw2ite" },
					"selectable": false
				},
				{
					"type": "textbox",
					"version": "5.3.0",
					"originX": "left",
					"originY": "top",
					"left": 448.48,
					"top": 231.82,
					"width": 106.59,
					"height": 22.6,
					"fill": "rgb(0,0,0)",
					"stroke": null,
					"strokeWidth": 1,
					"strokeDashArray": null,
					"strokeLineCap": "butt",
					"strokeDashOffset": 0,
					"strokeLineJoin": "miter",
					"strokeUniform": false,
					"strokeMiterLimit": 4,
					"scaleX": 1.65,
					"scaleY": 1.65,
					"angle": 0,
					"flipX": false,
					"flipY": false,
					"opacity": 1,
					"shadow": null,
					"visible": true,
					"backgroundColor": "",
					"fillRule": "nonzero",
					"paintFirst": "fill",
					"globalCompositeOperation": "source-over",
					"skewX": 0,
					"skewY": 0,
					"fontFamily": "Inter",
					"fontWeight": "normal",
					"fontSize": 20,
					"text": "Artboard 3",
					"underline": false,
					"overline": false,
					"linethrough": false,
					"textAlign": "left",
					"fontStyle": "normal",
					"lineHeight": 1.16,
					"textBackgroundColor": "",
					"charSpacing": 0,
					"styles": [],
					"direction": "ltr",
					"path": null,
					"pathStartOffset": 0,
					"pathSide": "left",
					"pathAlign": "baseline",
					"minWidth": 20,
					"splitByGrapheme": false,
					"selectable": true
				},
				{
					"type": "image",
					"version": "5.3.0",
					"originX": "left",
					"originY": "top",
					"left": 414.05,
					"top": 285.33,
					"width": 4762,
					"height": 3566,
					"fill": "rgb(0,0,0)",
					"stroke": null,
					"strokeWidth": 0,
					"strokeDashArray": null,
					"strokeLineCap": "butt",
					"strokeDashOffset": 0,
					"strokeLineJoin": "miter",
					"strokeUniform": false,
					"strokeMiterLimit": 4,
					"scaleX": 0.05,
					"scaleY": 0.05,
					"angle": 0,
					"flipX": false,
					"flipY": false,
					"opacity": 1,
					"shadow": null,
					"visible": true,
					"backgroundColor": "",
					"fillRule": "nonzero",
					"paintFirst": "fill",
					"globalCompositeOperation": "source-over",
					"skewX": 0,
					"skewY": 0,
					"cropX": 0,
					"cropY": 0,
					"selectable": true,
					"src": "https://ik.imagekit.io/mfsshclpl/A%20man%20and%20a%20woman%20walking%20in%20the%20desert.jpg?updatedAt=1699352535525",
					"crossOrigin": "anonymous",
					"filters": []
				}
			]
		}
	},
	{
		"name": "Square 2",
		"width": 200,
		"height": 200,
		"number": 1,
		"id": "x7wtgffgs",
		"state": {
			"version": "5.3.0",
			"objects": [
				{
					"type": "rect",
					"version": "5.3.0",
					"originX": "left",
					"originY": "top",
					"left": 433.5,
					"top": 336.5,
					"width": 200,
					"height": 200,
					"fill": "#fff",
					"stroke": null,
					"strokeWidth": 1,
					"strokeDashArray": null,
					"strokeLineCap": "butt",
					"strokeDashOffset": 0,
					"strokeLineJoin": "miter",
					"strokeUniform": false,
					"strokeMiterLimit": 4,
					"scaleX": 1,
					"scaleY": 1,
					"angle": 0,
					"flipX": false,
					"flipY": false,
					"opacity": 1,
					"shadow": null,
					"visible": true,
					"backgroundColor": "",
					"fillRule": "nonzero",
					"paintFirst": "fill",
					"globalCompositeOperation": "source-over",
					"skewX": 0,
					"skewY": 0,
					"rx": 0,
					"ry": 0,
					"data": { "type": "artboard", "id": "x7wtgffgs" },
					"selectable": false
				},
				{
					"type": "textbox",
					"version": "5.3.0",
					"originX": "left",
					"originY": "top",
					"left": 456.36,
					"top": 350.31,
					"width": 116.26,
					"height": 22.6,
					"fill": "rgb(0,0,0)",
					"stroke": null,
					"strokeWidth": 1,
					"strokeDashArray": null,
					"strokeLineCap": "butt",
					"strokeDashOffset": 0,
					"strokeLineJoin": "miter",
					"strokeUniform": false,
					"strokeMiterLimit": 4,
					"scaleX": 1.49,
					"scaleY": 1.49,
					"angle": 0,
					"flipX": false,
					"flipY": false,
					"opacity": 1,
					"shadow": null,
					"visible": true,
					"backgroundColor": "",
					"fillRule": "nonzero",
					"paintFirst": "fill",
					"globalCompositeOperation": "source-over",
					"skewX": 0,
					"skewY": 0,
					"fontFamily": "Inter",
					"fontWeight": "normal",
					"fontSize": 20,
					"text": "Artboard 4",
					"underline": false,
					"overline": false,
					"linethrough": false,
					"textAlign": "left",
					"fontStyle": "normal",
					"lineHeight": 1.16,
					"textBackgroundColor": "",
					"charSpacing": 0,
					"styles": [],
					"direction": "ltr",
					"path": null,
					"pathStartOffset": 0,
					"pathSide": "left",
					"pathAlign": "baseline",
					"minWidth": 20,
					"splitByGrapheme": false,
					"selectable": true
				},
				{
					"type": "image",
					"version": "5.3.0",
					"originX": "left",
					"originY": "top",
					"left": 457,
					"top": 403.19,
					"width": 4762,
					"height": 3566,
					"fill": "rgb(0,0,0)",
					"stroke": null,
					"strokeWidth": 0,
					"strokeDashArray": null,
					"strokeLineCap": "butt",
					"strokeDashOffset": 0,
					"strokeLineJoin": "miter",
					"strokeUniform": false,
					"strokeMiterLimit": 4,
					"scaleX": 0.03,
					"scaleY": 0.03,
					"angle": 0,
					"flipX": false,
					"flipY": false,
					"opacity": 1,
					"shadow": null,
					"visible": true,
					"backgroundColor": "",
					"fillRule": "nonzero",
					"paintFirst": "fill",
					"globalCompositeOperation": "source-over",
					"skewX": 0,
					"skewY": 0,
					"cropX": 0,
					"cropY": 0,
					"selectable": true,
					"src": "https://ik.imagekit.io/mfsshclpl/A%20man%20and%20a%20woman%20walking%20in%20the%20desert.jpg?updatedAt=1699352535525",
					"crossOrigin": "anonymous",
					"filters": []
				}
			]
		}
	},
	{
		"name": "Long board",
		"width": 500,
		"height": 1000,
		"number": 1,
		"id": "f6ix46rpi",
		"state": {
			"version": "5.3.0",
			"objects": [
				{
					"type": "rect",
					"version": "5.3.0",
					"originX": "left",
					"originY": "top",
					"left": 283.5,
					"top": -63.5,
					"width": 500,
					"height": 1000,
					"fill": "#fff",
					"stroke": null,
					"strokeWidth": 1,
					"strokeDashArray": null,
					"strokeLineCap": "butt",
					"strokeDashOffset": 0,
					"strokeLineJoin": "miter",
					"strokeUniform": false,
					"strokeMiterLimit": 4,
					"scaleX": 1,
					"scaleY": 1,
					"angle": 0,
					"flipX": false,
					"flipY": false,
					"opacity": 1,
					"shadow": null,
					"visible": true,
					"backgroundColor": "",
					"fillRule": "nonzero",
					"paintFirst": "fill",
					"globalCompositeOperation": "source-over",
					"skewX": 0,
					"skewY": 0,
					"rx": 0,
					"ry": 0,
					"data": { "type": "artboard", "id": "f6ix46rpi" },
					"selectable": false
				},
				{
					"type": "textbox",
					"version": "5.3.0",
					"originX": "left",
					"originY": "top",
					"left": 346.13,
					"top": 97.8,
					"width": 144.02,
					"height": 22.6,
					"fill": "rgb(0,0,0)",
					"stroke": null,
					"strokeWidth": 1,
					"strokeDashArray": null,
					"strokeLineCap": "butt",
					"strokeDashOffset": 0,
					"strokeLineJoin": "miter",
					"strokeUniform": false,
					"strokeMiterLimit": 4,
					"scaleX": 2.72,
					"scaleY": 2.72,
					"angle": 0,
					"flipX": false,
					"flipY": false,
					"opacity": 1,
					"shadow": null,
					"visible": true,
					"backgroundColor": "",
					"fillRule": "nonzero",
					"paintFirst": "fill",
					"globalCompositeOperation": "source-over",
					"skewX": 0,
					"skewY": 0,
					"fontFamily": "Inter",
					"fontWeight": "normal",
					"fontSize": 20,
					"text": "New Test Text",
					"underline": false,
					"overline": false,
					"linethrough": false,
					"textAlign": "left",
					"fontStyle": "normal",
					"lineHeight": 1.16,
					"textBackgroundColor": "",
					"charSpacing": 0,
					"styles": [],
					"direction": "ltr",
					"path": null,
					"pathStartOffset": 0,
					"pathSide": "left",
					"pathAlign": "baseline",
					"minWidth": 20,
					"splitByGrapheme": false,
					"selectable": true
				},
				{
					"type": "image",
					"version": "5.3.0",
					"originX": "left",
					"originY": "top",
					"left": 330.18,
					"top": 365.49,
					"width": 1400,
					"height": 930,
					"fill": "rgb(0,0,0)",
					"stroke": null,
					"strokeWidth": 0,
					"strokeDashArray": null,
					"strokeLineCap": "butt",
					"strokeDashOffset": 0,
					"strokeLineJoin": "miter",
					"strokeUniform": false,
					"strokeMiterLimit": 4,
					"scaleX": 0.29,
					"scaleY": 0.29,
					"angle": 0,
					"flipX": false,
					"flipY": false,
					"opacity": 1,
					"shadow": null,
					"visible": true,
					"backgroundColor": "",
					"fillRule": "nonzero",
					"paintFirst": "fill",
					"globalCompositeOperation": "source-over",
					"skewX": 0,
					"skewY": 0,
					"cropX": 0,
					"cropY": 0,
					"selectable": true,
					"src": "https://miro.medium.com/v2/resize:fit:1400/format:webp/0*MoaTV0fSycy_nxoD",
					"crossOrigin": "anonymous",
					"filters": []
				},
				{
					"type": "textbox",
					"version": "5.3.0",
					"originX": "left",
					"originY": "top",
					"left": 314.5,
					"top": 310.5,
					"width": 146.5,
					"height": 22.6,
					"fill": "rgb(0,0,0)",
					"stroke": null,
					"strokeWidth": 1,
					"strokeDashArray": null,
					"strokeLineCap": "butt",
					"strokeDashOffset": 0,
					"strokeLineJoin": "miter",
					"strokeUniform": false,
					"strokeMiterLimit": 4,
					"scaleX": 1,
					"scaleY": 1,
					"angle": 0,
					"flipX": false,
					"flipY": false,
					"opacity": 1,
					"shadow": null,
					"visible": true,
					"backgroundColor": "",
					"fillRule": "nonzero",
					"paintFirst": "fill",
					"globalCompositeOperation": "source-over",
					"skewX": 0,
					"skewY": 0,
					"fontFamily": "Inter",
					"fontWeight": "normal",
					"fontSize": 20,
					"text": "Helleow",
					"underline": false,
					"overline": false,
					"linethrough": false,
					"textAlign": "left",
					"fontStyle": "normal",
					"lineHeight": 1.16,
					"textBackgroundColor": "",
					"charSpacing": 0,
					"styles": [],
					"direction": "ltr",
					"path": null,
					"pathStartOffset": 0,
					"pathSide": "left",
					"pathAlign": "baseline",
					"minWidth": 20,
					"splitByGrapheme": false,
					"selectable": true
				}
			]
		}
	}
]
